login_required/__init__.py
login_required/apps.py
login_required/middleware.py
django_login_required_middleware-0.8.0.dist-info/LICENSE
django_login_required_middleware-0.8.0.dist-info/METADATA
django_login_required_middleware-0.8.0.dist-info/WHEEL
django_login_required_middleware-0.8.0.dist-info/top_level.txt
django_login_required_middleware-0.8.0.dist-info/RECORD
