Metadata-Version: 2.1
Name: django-login-required-middleware
Version: 0.8.0
Summary: Requires login to all requests through middleware.
Home-page: https://github.com/CleitonDeLima/django-login-required-middleware
Author: Cleiton de Lima
Author-email: cleiton.limapin@gmail.com
License: MIT
Platform: UNKNOWN
Classifier: Environment :: Web Environment
Classifier: Framework :: Django
Classifier: Framework :: Django :: 2.2
Classifier: Framework :: Django :: 3.0
Classifier: Intended Audience :: Developers
Classifier: Operating System :: OS Independent
Classifier: Programming Language :: Python
Classifier: Programming Language :: Python :: 3
Classifier: Topic :: Internet :: WWW/HTTP
Classifier: Topic :: Internet :: WWW/HTTP :: Dynamic Content
License-File: LICENSE
